{
  "version": "10.0.1",
  "packageId": "DMNSN.ProjectTemplates",
  "title": "DMNSN Project Templates",
  "description": "Collection of DMNSN .NET project templates for dotnet new and Visual Studio.",
  "projectUrl": "https://github.com/DevilDogTG/VisualStudio.ProjectTemplates",
  "repository": {
    "type": "git",
    "url": "https://github.com/DevilDogTG/VisualStudio.ProjectTemplates"
  },
  "readme": "README.md",
  "license": "LICENSE",
  "icon": "logo.png",
  "templates": {
    "DMNSN.ConsoleApp.CSharp": {
      "hash": "b75318f669bef01942ed179068fa219a7326df350458babeaefcecfa74a60440"
    },
    "DMNSN.WorkerApp.CSharp": {
      "hash": "3e3dd693571dec25ca5b0beaea6695f25a9d7e7c91f1d7121ff3b3716977147d"
    },
    "DMNSN.WebApi.GraphQl.CSharp": {
      "hash": "fc9bb3a541618d3332d887d5bc035a90dac23ddcdd7a1308b2f01b68caae2cd9"
    },
    "DMNSN.ClassLibrary.CSharp": {
      "hash": "fd4b32396e05363831d6a4a3ef49b72674f55b4568eb75a51751f872f5c9311b"
    },
    "DMNSN.WebApi.Rest.CSharp": {
      "hash": "b78c317173ce6a933792ce1f66a4b35a3d7e460fe3adfbbc8f73d29f64cb792a"
    }
  }
}
